ksoftapi/__init__.py
ksoftapi/client.py
ksoftapi/errors.py
ksoftapi/events.py
ksoftapi/http.py
ksoftapi/models.py
ksoftapi/apis/__init__.py
ksoftapi/apis/bans.py
ksoftapi/apis/images.py
ksoftapi/apis/kumo.py
ksoftapi/apis/music.py
ksoftapi-0.4.1.dist-info/LICENSE
ksoftapi-0.4.1.dist-info/METADATA
ksoftapi-0.4.1.dist-info/WHEEL
ksoftapi-0.4.1.dist-info/top_level.txt
ksoftapi-0.4.1.dist-info/RECORD
