Metadata-Version: 2.1
Name: ksoftapi
Version: 0.4.1
Summary: The official KSoft.SI API Wrapper.
Home-page: https://github.com/KSoft-Si/ksoftapi.py
Author: AndyTempel
Author-email: support@ksoft.si
License: UNKNOWN
Download-URL: https://github.com/KSoft-Si/ksoftapi.py/archive/0.4.1.tar.gz
Keywords: ksoftapi
Platform: UNKNOWN
Classifier: Development Status :: 3 - Alpha
Classifier: License :: OSI Approved :: GNU General Public License (GPL)
Classifier: Intended Audience :: Developers
Classifier: Natural Language :: English
Classifier: Operating System :: OS Independent
Classifier: Programming Language :: Python :: 3.6
Classifier: Topic :: Internet
Classifier: Topic :: Software Development :: Libraries
Classifier: Topic :: Software Development :: Libraries :: Python Modules
Classifier: Topic :: Utilities
Requires-Python: >=3.6
Requires-Dist: aiohttp
